datacyclist/__init__.py
datacyclist/fastestsegment.py
datacyclist/make_dataset.py
datacyclist/plot_activity_summary.py
datacyclist/plot_history.py
datacyclist/powercurve.py
datacyclist/utils.py
datacyclist-0.2.0.dist-info/LICENSE
datacyclist-0.2.0.dist-info/METADATA
datacyclist-0.2.0.dist-info/WHEEL
datacyclist-0.2.0.dist-info/top_level.txt
datacyclist-0.2.0.dist-info/RECORD
