Metadata-Version: 2.1
Name: datacyclist
Version: 0.2.0
Summary: datacyclist, a package to analyze cycling data.
Home-page: https://pypi.org/project/datacyclist/
Download-URL: https://github.com/lucabasa/datacyclist
Author: Luca Basanisi
Author-email: luca.basanisi@gmail.com
Maintainer: Luca Basanisi
Maintainer-email: luca.basanisi@gmail.com
License: Apache 2.0
Project-URL: Source Code, https://github.com/lucabasa/datacyclist
Classifier: Development Status :: 4 - Beta
Classifier: Programming Language :: Python
Classifier: Programming Language :: Python :: 3.10
Classifier: Intended Audience :: Science/Research
Classifier: Intended Audience :: Developers
Classifier: Operating System :: Microsoft :: Windows
Classifier: Operating System :: POSIX
Classifier: Operating System :: Unix
Classifier: Operating System :: MacOS
Requires-Python: >=3.7
License-File: LICENSE
Requires-Dist: matplotlib >=3.5.3
Requires-Dist: pandas >=1.3.5
Requires-Dist: scikit-learn >=1.0.2
Requires-Dist: seaborn >=0.12.0
Requires-Dist: fitdecode ==0.10.0
